tdub/__init__.py
tdub/__main__.py
tdub/art.py
tdub/batch.py
tdub/config.py
tdub/data.py
tdub/features.py
tdub/frames.py
tdub/hist.py
tdub/math.py
tdub/ml_apply.py
tdub/ml_train.py
tdub/py.typed
tdub/rex.py
tdub/root.py
tdub/version.py
tdub/internal/__init__.py
tdub/internal/cramped.py
tdub/internal/drds.py
tdub/internal/rexindex.py
tdub/internal/shapecomps.py
tdub/internal/stab_tests.py
tdub/old/__init__.py
tdub/old/raw_art.py
tdub/old/rex_art.py
tdub-0.0.79.dist-info/LICENSE
tdub-0.0.79.dist-info/METADATA
tdub-0.0.79.dist-info/WHEEL
tdub-0.0.79.dist-info/entry_points.txt
tdub-0.0.79.dist-info/top_level.txt
tdub-0.0.79.dist-info/RECORD
