Metadata-Version: 2.1
Name: tdub
Version: 0.0.79
Summary: tW analysis tools.
Home-page: https://github.com/douglasdavis/tdub
Author: Doug Davis
Author-email: ddavis@ddavis.io
Maintainer: Doug Davis
Maintainer-email: ddavis@ddavis.io
License: BSD 3-clause
Classifier: Development Status :: 3 - Alpha
Classifier: Intended Audience :: Science/Research
Classifier: License :: OSI Approved :: BSD License
Classifier: Programming Language :: Python :: 3 :: Only
Classifier: Programming Language :: Python :: 3.8
Classifier: Programming Language :: Python :: 3.9
Requires-Python: >=3.8
License-File: LICENSE
Requires-Dist: click (>=7.1)
Requires-Dist: formulate (>=0.0.8)
Requires-Dist: joblib (>=0.15)
Requires-Dist: lz4 (>=3.0)
Requires-Dist: matplotlib (>=3.2)
Requires-Dist: numexpr (>=2.7.0)
Requires-Dist: pandas (>=1.1)
Requires-Dist: pycondor (==0.5.0)
Requires-Dist: pygram11 (>=0.12.2)
Requires-Dist: pyyaml (>=5.1)
Requires-Dist: scikit-learn (>=0.23.2)
Requires-Dist: uproot (>=4.0.0)
Requires-Dist: xxhash (>=1.4)
Requires-Dist: requests (>=2.20)
